ugly_switch.py
tests/__init__.py
ugly_switch-0.1.2.dist-info/LICENCE
ugly_switch-0.1.2.dist-info/METADATA
ugly_switch-0.1.2.dist-info/WHEEL
ugly_switch-0.1.2.dist-info/top_level.txt
ugly_switch-0.1.2.dist-info/RECORD
