Metadata-Version: 2.1
Name: ugly-switch
Version: 0.1.2
Summary: An ugly pseudo solution for using switches in python. 
Home-page: https://github.com/RoW171/ugly_switch
Author: Robin 'r0w' Weiland
Author-email: robin.weiland@gmx.de
License: MIT
Keywords: switch
Platform: UNKNOWN
Classifier: Development Status :: 5 - Production/Stable
Classifier: Intended Audience :: Developers
Classifier: Topic :: Software Development
Classifier: License :: OSI Approved :: MIT License
Classifier: Programming Language :: Python :: 3.7
Classifier: Operating System :: OS Independent
Requires-Python: >=3.7
